{
  "row_count": 21618,
  "time_span": [
    1970,
    2025
  ],
  "global_sales_total": 16894.45,
  "region_share": {
    "北美销量": 0.5076312696817217,
    "欧洲销量": 0.2905576323325326,
    "日本销量": 0.10311779728699709,
    "其他地区销量": 0.09869330069874856
  },
  "top_genres": [
    [
      "动作冒险",
      2246.46
    ],
    [
      "射击",
      2211.46
    ],
    [
      "角色扮演",
      2181.92
    ],
    [
      "体育",
      1855.78
    ],
    [
      "动作",
      1771.83
    ],
    [
      "平台跳跃",
      1410.93
    ],
    [
      "竞速",
      1041.31
    ],
    [
      "其他",
      929.41
    ],
    [
      "模拟",
      780.81
    ],
    [
      "格斗",
      774.27
    ]
  ],
  "top_publishers": [
    [
      "Nintendo",
      2651.7
    ],
    [
      "Electronic Arts",
      1076.85
    ],
    [
      "Activision",
      1070.1
    ],
    [
      "Ubisoft",
      775.89
    ],
    [
      "Rockstar Games",
      697.91
    ],
    [
      "Capcom",
      679.04
    ],
    [
      "EA Sports",
      639.99
    ],
    [
      "Sony Computer Entertainment",
      611.06
    ],
    [
      "Sega",
      437.42
    ],
    [
      "THQ",
      413.66
    ]
  ],
  "top_platforms": [
    [
      "全平台",
      5003.03
    ],
    [
      "PlayStation 家族",
      3815.13
    ],
    [
      "任天堂家族",
      3643.81
    ],
    [
      "Xbox 家族",
      1548.63
    ],
    [
      "个人计算机",
      1545.71
    ],
    [
      "其他平台",
      779.29
    ],
    [
      "PlayStation 掌机",
      356.39
    ],
    [
      "世嘉平台",
      101.04
    ],
    [
      "雅达利平台",
      97.36
    ],
    [
      "SNK 平台",
      1.44
    ]
  ],
  "time_series": {
    "yearly_sales": {
      "1970": 155.06,
      "1977": 2.5,
      "1978": 5.36,
      "1979": 0.79,
      "1980": 7.89,
      "1981": 14.67,
      "1982": 48.01,
      "1983": 25.68,
      "1984": 14.29,
      "1985": 99.52,
      "1986": 23.25,
      "1987": 36.9,
      "1988": 32.02,
      "1989": 95.81,
      "1990": 61.79,
      "1991": 84.83,
      "1992": 100.35,
      "1993": 83.47,
      "1994": 94.18,
      "1995": 122.78,
      "1996": 191.56,
      "1997": 218.15,
      "1998": 309.12,
      "1999": 302.63,
      "2000": 301.66,
      "2001": 424.05,
      "2002": 456.96,
      "2003": 475.87,
      "2004": 556.94,
      "2005": 562.92,
      "2006": 629.16,
      "2007": 766.48,
      "2008": 891.7,
      "2009": 828.42,
      "2010": 872.96,
      "2011": 1286.02,
      "2012": 642.79,
      "2013": 830.69,
      "2014": 647.24,
      "2015": 693.24,
      "2016": 672.1,
      "2017": 842.81,
      "2018": 702.89,
      "2019": 405.98,
      "2020": 358.26,
      "2021": 239.99,
      "2022": 216.32,
      "2023": 216.9,
      "2024": 161.76,
      "2025": 79.73
    },
    "yearly_releases": {
      "1970": 532,
      "1977": 3,
      "1978": 9,
      "1979": 5,
      "1980": 14,
      "1981": 20,
      "1982": 60,
      "1983": 47,
      "1984": 25,
      "1985": 24,
      "1986": 38,
      "1987": 36,
      "1988": 37,
      "1989": 40,
      "1990": 35,
      "1991": 48,
      "1992": 61,
      "1993": 86,
      "1994": 126,
      "1995": 222,
      "1996": 329,
      "1997": 300,
      "1998": 364,
      "1999": 377,
      "2000": 434,
      "2001": 535,
      "2002": 839,
      "2003": 842,
      "2004": 813,
      "2005": 997,
      "2006": 1070,
      "2007": 1263,
      "2008": 1575,
      "2009": 1654,
      "2010": 1449,
      "2011": 1340,
      "2012": 793,
      "2013": 682,
      "2014": 802,
      "2015": 787,
      "2016": 823,
      "2017": 837,
      "2018": 763,
      "2019": 118,
      "2020": 105,
      "2021": 63,
      "2022": 60,
      "2023": 52,
      "2024": 48,
      "2025": 36
    },
    "cagr": -0.013483098288068596,
    "volatility": 1.617094836700752,
    "boom_periods": [
      {
        "year": 1980,
        "yoy": 8.987341772151899
      },
      {
        "year": 1985,
        "yoy": 5.9643107067879635
      },
      {
        "year": 1982,
        "yoy": 2.27266530334015
      }
    ],
    "bust_periods": [
      {
        "year": 1977,
        "yoy": -0.9838772088223914
      },
      {
        "year": 1979,
        "yoy": -0.8526119402985075
      },
      {
        "year": 1986,
        "yoy": -0.766378617363344
      }
    ],
    "recent_release_density": 51.8
  },
  "tier_contributions": {
    "sales_by_tier": [
      {
        "tier": "1-5M",
        "global_sales": 5605.88,
        "region_share": {
          "北美销量": 0.5224001081477762,
          "欧洲销量": 0.3207431297193951,
          "日本销量": 0.04613275139529943,
          "其他地区销量": 0.1107240107375292
        }
      },
      {
        "tier": "10-20M",
        "global_sales": 2177.67,
        "region_share": {
          "北美销量": 0.46116661295520467,
          "欧洲销量": 0.39130590468005877,
          "日本销量": 0.02191427650660651,
          "其他地区销量": 0.12561320585813013
        }
      },
      {
        "tier": "20M+",
        "global_sales": 2767.94,
        "region_share": {
          "北美销量": 0.31333005410723075,
          "欧洲销量": 0.4845056566650271,
          "日本销量": 0.04869650762420069,
          "其他地区销量": 0.15346778160354158
        }
      },
      {
        "tier": "5-10M",
        "global_sales": 2203.52,
        "region_share": {
          "北美销量": 0.4528133505867655,
          "欧洲销量": 0.3939137030922315,
          "日本销量": 0.028155816340190088,
          "其他地区销量": 0.125117129980813
        }
      },
      {
        "tier": "<1M",
        "global_sales": 4139.44,
        "region_share": {
          "北美销量": 0.5086344596653319,
          "欧洲销量": 0.2423742532754317,
          "日本销量": 0.16618603405771898,
          "其他地区销量": 0.0828052530015173
        }
      }
    ],
    "score_sales_matrix": [
      {
        "score_tier": "6_to_8",
        "sales_tier": "1-5M",
        "global_sales": 892.19
      },
      {
        "score_tier": "6_to_8",
        "sales_tier": "10-20M",
        "global_sales": 127.17
      },
      {
        "score_tier": "6_to_8",
        "sales_tier": "20M+",
        "global_sales": 235.93
      },
      {
        "score_tier": "6_to_8",
        "sales_tier": "5-10M",
        "global_sales": 231.17
      },
      {
        "score_tier": "6_to_8",
        "sales_tier": "<1M",
        "global_sales": 596.59
      },
      {
        "score_tier": "<=6",
        "sales_tier": "1-5M",
        "global_sales": 130.52
      },
      {
        "score_tier": "<=6",
        "sales_tier": "20M+",
        "global_sales": 28.02
      },
      {
        "score_tier": "<=6",
        "sales_tier": "5-10M",
        "global_sales": 11.13
      },
      {
        "score_tier": "<=6",
        "sales_tier": "<1M",
        "global_sales": 198.33
      },
      {
        "score_tier": ">=8",
        "sales_tier": "1-5M",
        "global_sales": 1503.97
      },
      {
        "score_tier": ">=8",
        "sales_tier": "10-20M",
        "global_sales": 976.46
      },
      {
        "score_tier": ">=8",
        "sales_tier": "20M+",
        "global_sales": 1797.63
      },
      {
        "score_tier": ">=8",
        "sales_tier": "5-10M",
        "global_sales": 886.46
      },
      {
        "score_tier": ">=8",
        "sales_tier": "<1M",
        "global_sales": 342.62
      }
    ],
    "tier_lift": [
      {
        "tier": "1-5M",
        "avg_sales": 2.1019,
        "lift": 2.689574043546845
      },
      {
        "tier": "10-20M",
        "avg_sales": 13.9594,
        "lift": 17.862334032774076
      },
      {
        "tier": "20M+",
        "avg_sales": 40.705,
        "lift": 52.08578497672312
      },
      {
        "tier": "5-10M",
        "avg_sales": 7.2247,
        "lift": 9.24466701194771
      },
      {
        "tier": "<1M",
        "avg_sales": 0.2247,
        "lift": 0.287524281642788
      }
    ]
  },
  "platform_lifecycle": [
    {
      "platform": "松下平台",
      "year_span": [
        1994,
        1995
      ],
      "momentum": 1190000.0000000002,
      "recent_sales": 1.1900000000000002,
      "total_sales": 1.1900000000000002,
      "retention_share": 1.0
    },
    {
      "platform": "世嘉平台",
      "year_span": [
        1990,
        2020
      ],
      "momentum": 150000.0,
      "recent_sales": 0.15,
      "total_sales": 101.03999999999999,
      "retention_share": 0.0014845605700712589
    },
    {
      "platform": "SNK 平台",
      "year_span": [
        1993,
        1996
      ],
      "momentum": 19.57114898358595,
      "recent_sales": 1.37,
      "total_sales": 1.44,
      "retention_share": 1.0
    },
    {
      "platform": "万代平台",
      "year_span": [
        1999,
        2002
      ],
      "momentum": 2.1086910680628956,
      "recent_sales": 0.9700000000000001,
      "total_sales": 1.4300000000000002,
      "retention_share": 1.0
    },
    {
      "platform": "雅达利平台",
      "year_span": [
        1970,
        1990
      ],
      "momentum": 1.2079201940989137,
      "recent_sales": 2.44,
      "total_sales": 97.36,
      "retention_share": 0.041187345932621196
    },
    {
      "platform": "个人计算机",
      "year_span": [
        1970,
        2025
      ],
      "momentum": 0.8679495542808636,
      "recent_sales": 52.32000000000001,
      "total_sales": 1545.71,
      "retention_share": 0.05158147388578711
    },
    {
      "platform": "全平台",
      "year_span": [
        1970,
        2025
      ],
      "momentum": 0.6570659236419564,
      "recent_sales": 297.71,
      "total_sales": 5003.030000000001,
      "retention_share": 0.11084282924547721
    },
    {
      "platform": "PlayStation 家族",
      "year_span": [
        1970,
        2025
      ],
      "momentum": 0.4191858037245908,
      "recent_sales": 20.8,
      "total_sales": 3815.13,
      "retention_share": 0.008324749091118782
    },
    {
      "platform": "其他平台",
      "year_span": [
        1970,
        2025
      ],
      "momentum": 0.3611764205701587,
      "recent_sales": 87.56,
      "total_sales": 779.2900000000001,
      "retention_share": 0.315184334458289
    },
    {
      "platform": "PlayStation 掌机",
      "year_span": [
        1970,
        2020
      ],
      "momentum": 0.12525150275394856,
      "recent_sales": 2.49,
      "total_sales": 356.39,
      "retention_share": 0.04076994303992817
    },
    {
      "platform": "Xbox 家族",
      "year_span": [
        1970,
        2022
      ],
      "momentum": 0.07011149152967955,
      "recent_sales": 6.54,
      "total_sales": 1548.6299999999999,
      "retention_share": 0.031472979343032226
    },
    {
      "platform": "任天堂家族",
      "year_span": [
        1970,
        2020
      ],
      "momentum": 0.05293869479092594,
      "recent_sales": 7.53,
      "total_sales": 3643.8100000000004,
      "retention_share": 0.027276394762624834
    }
  ],
  "regional_resilience": {
    "platform_resilience": [
      {
        "platform": "PlayStation 家族",
        "hhi": 0.33255682890000315,
        "entropy": 1.7513218198402951,
        "dominant_region": "北美销量"
      },
      {
        "platform": "PlayStation 掌机",
        "hhi": 0.2732689715752045,
        "entropy": 1.9307396726138926,
        "dominant_region": "北美销量"
      },
      {
        "platform": "SNK 平台",
        "hhi": 1.0,
        "entropy": -0.0,
        "dominant_region": "日本销量"
      },
      {
        "platform": "Xbox 家族",
        "hhi": 0.4840161712813374,
        "entropy": 1.2823265663921597,
        "dominant_region": "北美销量"
      },
      {
        "platform": "万代平台",
        "hhi": 1.0,
        "entropy": -0.0,
        "dominant_region": "日本销量"
      },
      {
        "platform": "世嘉平台",
        "hhi": 0.48414223063226525,
        "entropy": 1.302097455792908,
        "dominant_region": "日本销量"
      },
      {
        "platform": "个人计算机",
        "hhi": 0.45417986187494086,
        "entropy": 1.2836679263638833,
        "dominant_region": "欧洲销量"
      },
      {
        "platform": "任天堂家族",
        "hhi": 0.394935019357857,
        "entropy": 1.6040634834730647,
        "dominant_region": "北美销量"
      },
      {
        "platform": "其他平台",
        "hhi": 0.3334069665602936,
        "entropy": 1.7540660910646482,
        "dominant_region": "北美销量"
      },
      {
        "platform": "松下平台",
        "hhi": 1.0,
        "entropy": -0.0,
        "dominant_region": "日本销量"
      },
      {
        "platform": "雅达利平台",
        "hhi": 0.876764415253,
        "entropy": 0.3865766655072627,
        "dominant_region": "北美销量"
      }
    ],
    "most_diversified": [
      {
        "platform": "PlayStation 掌机",
        "hhi": 0.2732689715752045,
        "entropy": 1.9307396726138926,
        "dominant_region": "北美销量"
      },
      {
        "platform": "PlayStation 家族",
        "hhi": 0.33255682890000315,
        "entropy": 1.7513218198402951,
        "dominant_region": "北美销量"
      },
      {
        "platform": "其他平台",
        "hhi": 0.3334069665602936,
        "entropy": 1.7540660910646482,
        "dominant_region": "北美销量"
      }
    ],
    "most_concentrated": [
      {
        "platform": "SNK 平台",
        "hhi": 1.0,
        "entropy": -0.0,
        "dominant_region": "日本销量"
      },
      {
        "platform": "万代平台",
        "hhi": 1.0,
        "entropy": -0.0,
        "dominant_region": "日本销量"
      },
      {
        "platform": "松下平台",
        "hhi": 1.0,
        "entropy": -0.0,
        "dominant_region": "日本销量"
      }
    ]
  },
  "quality_gap": {
    "quartiles": {
      "0.25": 6.5,
      "0.5": 7.5,
      "0.75": 8.35
    },
    "correlation": 0.16053022776683376,
    "score_gap": {
      "mean_gap": -0.3611353711790394,
      "std_gap": 1.1319601552165068,
      "share_positive": 0.2925764192139738
    },
    "largest_disagreements": [
      {
        "name": "Dragon Quest VII",
        "platform": "PlayStation 家族",
        "score_gap": 5.0,
        "global_sales": 4.3
      },
      {
        "name": "Sonic and the Black Knight",
        "platform": "任天堂家族",
        "score_gap": -3.7,
        "global_sales": 1.2
      },
      {
        "name": "DiRT 4",
        "platform": "个人计算机",
        "score_gap": 3.6999999999999993,
        "global_sales": 0.01
      },
      {
        "name": "FIFA 18",
        "platform": "其他平台",
        "score_gap": -3.3,
        "global_sales": 1.1
      },
      {
        "name": "Uncharted 3: Drake's Deception",
        "platform": "PlayStation 家族",
        "score_gap": 3.000000000000001,
        "global_sales": 9.3
      }
    ]
  },
  "cluster_insights": [
    {
      "label": "日本销量主导",
      "size": 8818,
      "avg_sales": 1.252861193014289,
      "top_genres": [
        "角色扮演",
        "冒险",
        "动作"
      ],
      "top_platforms": [
        "任天堂家族",
        "PlayStation 家族",
        "个人计算机"
      ]
    },
    {
      "label": "欧洲销量主导",
      "size": 5612,
      "avg_sales": 0.5868050605844619,
      "top_genres": [
        "动作",
        "体育",
        "竞速"
      ],
      "top_platforms": [
        "PlayStation 家族",
        "任天堂家族",
        "个人计算机"
      ]
    },
    {
      "label": "北美销量主导",
      "size": 7188,
      "avg_sales": 0.35525459098497497,
      "top_genres": [
        "体育",
        "动作",
        "其他"
      ],
      "top_platforms": [
        "任天堂家族",
        "Xbox 家族",
        "PlayStation 家族"
      ]
    }
  ],
  "innovation": {
    "region_share": {
      "NA_Sales": 3343.29,
      "EU_Sales": 1913.6299999999999,
      "JP_Sales": 679.1400000000001,
      "Other_Sales": 650.0
    },
    "top_genres": [
      [
        "动作冒险",
        2246.46
      ],
      [
        "射击",
        2211.46
      ],
      [
        "角色扮演",
        2181.92
      ],
      [
        "体育",
        1855.78
      ],
      [
        "动作",
        1771.83
      ],
      [
        "平台跳跃",
        1410.93
      ],
      [
        "竞速",
        1041.31
      ],
      [
        "其他",
        929.41
      ],
      [
        "模拟",
        780.81
      ],
      [
        "格斗",
        774.27
      ]
    ],
    "platform_share": [
      [
        "All",
        0.2961345293868696
      ],
      [
        "PlayStation",
        0.2258214975924046
      ],
      [
        "Nintendo",
        0.2156808892861265
      ],
      [
        "Xbox",
        0.09166501425024194
      ],
      [
        "PC",
        0.09149217642480223
      ],
      [
        "NS",
        0.04367351408302727
      ],
      [
        "PlayStation Portable",
        0.021095093359061703
      ],
      [
        "Sega",
        0.005980662288503029
      ],
      [
        "Atari",
        0.0057628392756201
      ],
      [
        "NS2",
        0.00077303493158996
      ],
      [
        "Int",
        0.00056231484304017
      ],
      [
        "XBL",
        0.0004125615216831563
      ],
      [
        "iOS",
        0.0003243668778800139
      ],
      [
        "PSN",
        0.0002965470909085528
      ],
      [
        "SNK",
        8.523509199766787e-05
      ],
      [
        "Bandai",
        8.464318163657295e-05
      ],
      [
        "Panasonic",
        7.043733297029498e-05
      ],
      [
        "VC",
        2.0716862638322055e-05
      ],
      [
        "Amig",
        1.775731083284747e-05
      ],
      [
        "WW",
        1.4797759027372893e-05
      ],
      [
        "OSX",
        1.3022027944088146e-05
      ],
      [
        "PCE",
        9.470565777518652e-06
      ],
      [
        "5200",
        2.367641444379663e-06
      ],
      [
        "GG",
        2.367641444379663e-06
      ],
      [
        "Mob",
        1.7757310832847473e-06
      ],
      [
        "PCFX",
        1.7757310832847473e-06
      ],
      [
        "ApII",
        5.919103610949158e-07
      ]
    ],
    "region_preference": [
      {
        "Genre": "视觉小说",
        "Region": "JP_Sales",
        "Preference": 0.7768822027130029
      },
      {
        "Genre": "桌游",
        "Region": "EU_Sales",
        "Preference": 0.35650119119687906
      },
      {
        "Genre": "策略",
        "Region": "JP_Sales",
        "Preference": 0.2095788605920743
      },
      {
        "Genre": "角色扮演",
        "Region": "JP_Sales",
        "Preference": 0.2018508992215498
      },
      {
        "Genre": "教育",
        "Region": "NA_Sales",
        "Preference": 0.2007020636516117
      },
      {
        "Genre": "沙盒",
        "Region": "JP_Sales",
        "Preference": 0.172014477845278
      },
      {
        "Genre": "益智",
        "Region": "JP_Sales",
        "Preference": 0.11983040988431766
      },
      {
        "Genre": "动作冒险",
        "Region": "EU_Sales",
        "Preference": 0.11033143616615393
      },
      {
        "Genre": "派对",
        "Region": "JP_Sales",
        "Preference": 0.08912776006356833
      },
      {
        "Genre": "格斗",
        "Region": "JP_Sales",
        "Preference": 0.06872879861988147
      },
      {
        "Genre": "竞速",
        "Region": "EU_Sales",
        "Preference": 0.049467269496794086
      },
      {
        "Genre": "大型多人",
        "Region": "JP_Sales",
        "Preference": 0.04618402870655826
      },
      {
        "Genre": "冒险",
        "Region": "JP_Sales",
        "Preference": 0.03716708894350175
      },
      {
        "Genre": "射击",
        "Region": "EU_Sales",
        "Preference": 0.03606001620547322
      },
      {
        "Genre": "平台跳跃",
        "Region": "NA_Sales",
        "Preference": 0.034008981600625154
      },
      {
        "Genre": "动作冒险",
        "Region": "Other_Sales",
        "Preference": 0.025237459724232483
      },
      {
        "Genre": "大型多人",
        "Region": "EU_Sales",
        "Preference": 0.02523184135167794
      },
      {
        "Genre": "其他",
        "Region": "NA_Sales",
        "Preference": 0.024226580070864867
      },
      {
        "Genre": "射击",
        "Region": "NA_Sales",
        "Preference": 0.023212935148340996
      },
      {
        "Genre": "模拟",
        "Region": "JP_Sales",
        "Preference": 0.016807541023782208
      },
      {
        "Genre": "动作",
        "Region": "NA_Sales",
        "Preference": 0.016624087302362978
      },
      {
        "Genre": "桌游",
        "Region": "JP_Sales",
        "Preference": 0.01452926153653232
      },
      {
        "Genre": "动作",
        "Region": "EU_Sales",
        "Preference": 0.013896888873122237
      },
      {
        "Genre": "大型多人",
        "Region": "Other_Sales",
        "Preference": 0.01194042647633202
      },
      {
        "Genre": "射击",
        "Region": "Other_Sales",
        "Preference": 0.010360300725526489
      },
      {
        "Genre": "音乐节奏",
        "Region": "JP_Sales",
        "Preference": 0.009710641661998282
      },
      {
        "Genre": "体育",
        "Region": "Other_Sales",
        "Preference": 0.009567458580865898
      },
      {
        "Genre": "竞速",
        "Region": "NA_Sales",
        "Preference": 0.007932373647461355
      },
      {
        "Genre": "竞速",
        "Region": "Other_Sales",
        "Preference": 0.007752442046199251
      },
      {
        "Genre": "其他",
        "Region": "Other_Sales",
        "Preference": 0.006605844600396746
      },
      {
        "Genre": "沙盒",
        "Region": "EU_Sales",
        "Preference": 0.005738663963763657
      },
      {
        "Genre": "体育",
        "Region": "NA_Sales",
        "Preference": 0.0053390524625246405
      },
      {
        "Genre": "益智",
        "Region": "NA_Sales",
        "Preference": 0.005197415577242515
      },
      {
        "Genre": "格斗",
        "Region": "NA_Sales",
        "Preference": 0.00242561180540668
      },
      {
        "Genre": "派对",
        "Region": "EU_Sales",
        "Preference": 0.0018494759065627031
      },
      {
        "Genre": "模拟",
        "Region": "NA_Sales",
        "Preference": 0.0018014348046458961
      },
      {
        "Genre": "动作",
        "Region": "Other_Sales",
        "Preference": 0.0012444604820107535
      },
      {
        "Genre": "音乐节奏",
        "Region": "EU_Sales",
        "Preference": -0.0003721609260411429
      },
      {
        "Genre": "模拟",
        "Region": "EU_Sales",
        "Preference": -0.0010435999346924407
      },
      {
        "Genre": "体育",
        "Region": "EU_Sales",
        "Preference": -0.002158207288142644
      },
      {
        "Genre": "音乐节奏",
        "Region": "Other_Sales",
        "Preference": -0.003446005490093232
      },
      {
        "Genre": "其他",
        "Region": "JP_Sales",
        "Preference": -0.0038285485240641126
      },
      {
        "Genre": "平台跳跃",
        "Region": "EU_Sales",
        "Preference": -0.004147627145511756
      },
      {
        "Genre": "冒险",
        "Region": "Other_Sales",
        "Preference": -0.005858621041598663
      },
      {
        "Genre": "音乐节奏",
        "Region": "NA_Sales",
        "Preference": -0.005892475245863893
      },
      {
        "Genre": "冒险",
        "Region": "EU_Sales",
        "Preference": -0.00853876324453856
      },
      {
        "Genre": "平台跳跃",
        "Region": "Other_Sales",
        "Preference": -0.011234364614373021
      },
      {
        "Genre": "体育",
        "Region": "JP_Sales",
        "Preference": -0.012748303755247686
      },
      {
        "Genre": "派对",
        "Region": "Other_Sales",
        "Preference": -0.014686838663207358
      },
      {
        "Genre": "格斗",
        "Region": "Other_Sales",
        "Preference": -0.014690485944746326
      },
      {
        "Genre": "教育",
        "Region": "Other_Sales",
        "Preference": -0.015359967365415214
      },
      {
        "Genre": "模拟",
        "Region": "Other_Sales",
        "Preference": -0.017565375893735552
      },
      {
        "Genre": "平台跳跃",
        "Region": "JP_Sales",
        "Preference": -0.018626989840740404
      },
      {
        "Genre": "角色扮演",
        "Region": "Other_Sales",
        "Preference": -0.019555260508348285
      },
      {
        "Genre": "冒险",
        "Region": "NA_Sales",
        "Preference": -0.02276970465736461
      },
      {
        "Genre": "其他",
        "Region": "EU_Sales",
        "Preference": -0.027003876147197514
      },
      {
        "Genre": "动作",
        "Region": "JP_Sales",
        "Preference": -0.0317654366574959
      },
      {
        "Genre": "沙盒",
        "Region": "Other_Sales",
        "Preference": -0.03520123720668507
      },
      {
        "Genre": "策略",
        "Region": "Other_Sales",
        "Preference": -0.037123439315977905
      },
      {
        "Genre": "桌游",
        "Region": "Other_Sales",
        "Preference": -0.03986977128698385
      },
      {
        "Genre": "益智",
        "Region": "Other_Sales",
        "Preference": -0.03988851982225453
      },
      {
        "Genre": "格斗",
        "Region": "EU_Sales",
        "Preference": -0.05646392448054177
      },
      {
        "Genre": "策略",
        "Region": "EU_Sales",
        "Preference": -0.06307230194729577
      },
      {
        "Genre": "竞速",
        "Region": "JP_Sales",
        "Preference": -0.06515208519045461
      },
      {
        "Genre": "动作冒险",
        "Region": "JP_Sales",
        "Preference": -0.06634269120496032
      },
      {
        "Genre": "动作冒险",
        "Region": "NA_Sales",
        "Preference": -0.06922620468542617
      },
      {
        "Genre": "射击",
        "Region": "JP_Sales",
        "Preference": -0.0696332520793406
      },
      {
        "Genre": "视觉小说",
        "Region": "Other_Sales",
        "Preference": -0.07608460504657465
      },
      {
        "Genre": "派对",
        "Region": "NA_Sales",
        "Preference": -0.07629039730692361
      },
      {
        "Genre": "角色扮演",
        "Region": "EU_Sales",
        "Preference": -0.07720147597921351
      },
      {
        "Genre": "教育",
        "Region": "EU_Sales",
        "Preference": -0.08222429899919931
      },
      {
        "Genre": "大型多人",
        "Region": "NA_Sales",
        "Preference": -0.08335629653456805
      },
      {
        "Genre": "益智",
        "Region": "EU_Sales",
        "Preference": -0.08513930563930552
      },
      {
        "Genre": "教育",
        "Region": "JP_Sales",
        "Preference": -0.10311779728699709
      },
      {
        "Genre": "角色扮演",
        "Region": "NA_Sales",
        "Preference": -0.10509416273398797
      },
      {
        "Genre": "策略",
        "Region": "NA_Sales",
        "Preference": -0.10938311932880046
      },
      {
        "Genre": "沙盒",
        "Region": "NA_Sales",
        "Preference": -0.14255190460235667
      },
      {
        "Genre": "视觉小说",
        "Region": "EU_Sales",
        "Preference": -0.27838371928905437
      },
      {
        "Genre": "桌游",
        "Region": "NA_Sales",
        "Preference": -0.3311606814464276
      },
      {
        "Genre": "视觉小说",
        "Region": "NA_Sales",
        "Preference": -0.4224138783773739
      }
    ],
    "platform_diversity": 2.5460210292429126,
    "publisher_moat": [
      {
        "Publisher": "Nintendo",
        "moat_score": 0.95
      },
      {
        "Publisher": "Electronic Arts",
        "moat_score": 0.5342685824188256
      },
      {
        "Publisher": "Activision",
        "moat_score": 0.5324867066410227
      },
      {
        "Publisher": "Capcom",
        "moat_score": 0.4292540634310065
      },
      {
        "Publisher": "Ubisoft",
        "moat_score": 0.40482068107251945
      }
    ],
    "gini": 0.779186116605524
  },
  "ml": {
    "regression": {
      "model": "LGBMRegressor",
      "mae": 0.7899164051051295,
      "rmse": 2.434681865347571,
      "r2": 0.14845676852308032,
      "n_estimators_used": 35
    },
    "regression_quantiles": {
      "p10_mean": 0.07564399771079929,
      "p50_mean": 0.3347317245476009,
      "p90_mean": 1.5335801589323217,
      "p10_median": 0.038505066726256754,
      "p50_median": 0.1842678010863406,
      "p90_median": 0.8524881631225351
    },
    "classification": {
      "model": "LGBMClassifier",
      "accuracy": 0.8725716928769658,
      "precision": 0.7050561797752809,
      "recall": 0.3601147776183644,
      "f1": 0.47673314339981004,
      "hit_threshold": 1.0,
      "support": 4324,
      "brier": 0.09420780779099797,
      "classification_report": {
        "0": {
          "precision": 0.8876008064516129,
          "recall": 0.9710504549214226,
          "f1-score": 0.9274522712310731,
          "support": 3627.0
        },
        "1": {
          "precision": 0.7050561797752809,
          "recall": 0.3601147776183644,
          "f1-score": 0.47673314339981004,
          "support": 697.0
        },
        "accuracy": 0.8725716928769658,
        "macro avg": {
          "precision": 0.7963284931134469,
          "recall": 0.6655826162698935,
          "f1-score": 0.7020927073154416,
          "support": 4324.0
        },
        "weighted avg": {
          "precision": 0.8581758284697898,
          "recall": 0.8725716928769658,
          "f1-score": 0.8547993498392159,
          "support": 4324.0
        }
      }
    },
    "calibration": {
      "curve": [
        {
          "predicted": 0.0446331078944963,
          "observed": 0.03557651093013288
        },
        {
          "predicted": 0.1437916305585678,
          "observed": 0.14699331848552338
        },
        {
          "predicted": 0.2480027415627728,
          "observed": 0.24754901960784315
        },
        {
          "predicted": 0.34544244875991326,
          "observed": 0.36619718309859156
        },
        {
          "predicted": 0.4527194357611966,
          "observed": 0.4482758620689655
        },
        {
          "predicted": 0.5480826879466736,
          "observed": 0.47692307692307695
        },
        {
          "predicted": 0.6380010419493225,
          "observed": 0.7246376811594203
        },
        {
          "predicted": 0.7525145914781803,
          "observed": 0.775
        },
        {
          "predicted": 0.8622571666206783,
          "observed": 0.9117647058823529
        },
        {
          "predicted": 0.945911058334892,
          "observed": 0.9387755102040817
        }
      ]
    },
    "clustering": [
      {
        "cluster": 0,
        "size": 4877,
        "avg_global_sales": 2.1736805413163833,
        "top_genres": [
          "角色扮演",
          "动作"
        ],
        "top_platforms": [
          "PC",
          "All"
        ],
        "dominant_region": "日本销量",
        "region_profile": {
          "北美销量": 0.0463,
          "欧洲销量": 0.0205,
          "日本销量": 0.0713,
          "其他地区销量": 0.0091
        }
      },
      {
        "cluster": 2,
        "size": 5607,
        "avg_global_sales": 0.5864437310504726,
        "top_genres": [
          "动作",
          "体育"
        ],
        "top_platforms": [
          "PlayStation",
          "Nintendo"
        ],
        "dominant_region": "欧洲销量",
        "region_profile": {
          "北美销量": 0.3473,
          "欧洲销量": 0.5266,
          "日本销量": 0.0153,
          "其他地区销量": 0.1107
        }
      },
      {
        "cluster": 3,
        "size": 7193,
        "avg_global_sales": 0.35569720561657175,
        "top_genres": [
          "体育",
          "动作"
        ],
        "top_platforms": [
          "Nintendo",
          "Xbox"
        ],
        "dominant_region": "北美销量",
        "region_profile": {
          "北美销量": 0.8172,
          "欧洲销量": 0.1178,
          "日本销量": 0.0099,
          "其他地区销量": 0.055
        }
      }
    ],
    "behavior_clusters": [
      {
        "cluster": 4,
        "size": 1255,
        "avg_global_sales": 6.121179282868526,
        "avg_age": 10.843027888446215,
        "score_median": 8.7,
        "cluster_purity": 0.8472077712802467,
        "top_genres": [
          "角色扮演",
          "动作冒险",
          "动作"
        ],
        "top_platforms": [
          "All",
          "PC"
        ],
        "region_profile": {
          "北美销量": 0.6196,
          "欧洲销量": 0.25,
          "日本销量": 0.0435,
          "其他地区销量": 0.087
        }
      },
      {
        "cluster": 1,
        "size": 967,
        "avg_global_sales": 2.655615305067218,
        "avg_age": 23.367114788004137,
        "score_median": 8.3,
        "cluster_purity": 0.9312041256452972,
        "top_genres": [
          "动作",
          "体育",
          "射击"
        ],
        "top_platforms": [
          "PlayStation",
          "Nintendo"
        ],
        "region_profile": {
          "北美销量": 0.4677,
          "欧洲销量": 0.3351,
          "日本销量": 0.0792,
          "其他地区销量": 0.1181
        }
      },
      {
        "cluster": 0,
        "size": 5308,
        "avg_global_sales": 0.8144404672192916,
        "avg_age": 18.309155990957045,
        "score_median": 7.4,
        "cluster_purity": 0.893570604615824,
        "top_genres": [
          "动作",
          "体育",
          "角色扮演"
        ],
        "top_platforms": [
          "Nintendo",
          "PlayStation"
        ],
        "region_profile": {
          "北美销量": 0.5644,
          "欧洲销量": 0.3053,
          "日本销量": 0.0286,
          "其他地区销量": 0.1018
        }
      }
    ],
    "top_features": [
      {
        "feature": "年份",
        "importance": 610.0
      },
      {
        "feature": "类型",
        "importance": 192.0
      },
      {
        "feature": "发行商",
        "importance": 163.0
      },
      {
        "feature": "平台",
        "importance": 85.0
      },
      {
        "feature": "年代",
        "importance": 0.0
      }
    ],
    "shap_features": [
      {
        "feature": "平台",
        "shap_importance": 0.3001806322905062
      },
      {
        "feature": "发行商",
        "shap_importance": 0.21991314834116873
      },
      {
        "feature": "类型",
        "shap_importance": 0.1414630388187675
      },
      {
        "feature": "年份",
        "shap_importance": 0.1097002782800608
      },
      {
        "feature": "年代",
        "shap_importance": 0.0
      }
    ],
    "similar_titles": [
      {
        "anchor": "Minecraft",
        "anchor_platform": "All",
        "candidate": "Lego Star Wars II: The Original Trilogy",
        "candidate_platform": "All",
        "similarity": 0.9794587663741734,
        "anchor_sales": 350.0,
        "candidate_sales": 8.2,
        "genre_match": true
      },
      {
        "anchor": "Minecraft",
        "anchor_platform": "All",
        "candidate": "Lego Star Wars: The Complete Saga",
        "candidate_platform": "All",
        "similarity": 0.9684358768282595,
        "anchor_sales": 350.0,
        "candidate_sales": 3.4,
        "genre_match": true
      },
      {
        "anchor": "Minecraft",
        "anchor_platform": "All",
        "candidate": "Marvel's Spider-Man: Miles Morales",
        "candidate_platform": "All",
        "similarity": 0.9524756198610841,
        "anchor_sales": 350.0,
        "candidate_sales": 14.4,
        "genre_match": true
      },
      {
        "anchor": "Minecraft",
        "anchor_platform": "All",
        "candidate": "Grand Theft Auto V",
        "candidate_platform": "All",
        "similarity": 0.9168403872824609,
        "anchor_sales": 350.0,
        "candidate_sales": 220.0,
        "genre_match": true
      },
      {
        "anchor": "Minecraft",
        "anchor_platform": "All",
        "candidate": "Elden Ring",
        "candidate_platform": "All",
        "similarity": 0.9071790502820862,
        "anchor_sales": 350.0,
        "candidate_sales": 30.0,
        "genre_match": true
      }
    ]
  }
}